bad_enums/__init__.py
bad_enums-1.0.0.dist-info/LICENSE
bad_enums-1.0.0.dist-info/WHEEL
bad_enums-1.0.0.dist-info/METADATA
bad_enums-1.0.0.dist-info/RECORD
