Metadata-Version: 2.1
Name: bad-enums
Version: 1.0.0
Summary: A very bad custom implementation of enums in Python.
Author: EmreTech
Requires-Python: >=3.9
Classifier: Programming Language :: Python :: 3
Classifier: Programming Language :: Python :: 3.10
Classifier: Programming Language :: Python :: 3.9
